boxcalendar
