Metadata-Version: 1.0
Name: boxcalendar
Version: 0.0.11
Summary: just a simple chinese calendar
Home-page: UNKNOWN
Author: CcdjhMarx
Author-email: ccdjh.marx@all.com
License: MIT License
Keywords: calendar,chinese
Platform: UNKNOWN
